xtce/__init__.py
xtce/msg_post_processor.py
xtce/xtce.py
xtce/xtce_generator.py
xtce/xtce_msg_parser.py
xtce_generator-1.2.5.dist-info/METADATA
xtce_generator-1.2.5.dist-info/WHEEL
xtce_generator-1.2.5.dist-info/top_level.txt
xtce_generator-1.2.5.dist-info/RECORD
