Metadata-Version: 2.1
Name: xtce-generator
Version: 1.2.5
Summary: A tool to generate xtce files from a sqlite database. 
Home-page: https://github.com/WindhoverLabs/xtce_generator
Author: Lorenzo Gomez
Author-email: lgomez@windhoverlabs.com
License: 3BSD-3-Clause
Platform: UNKNOWN
Requires-Python: >=3.6.0
Requires-Dist: PyYAML (~=5.3.1)
Requires-Dist: bitarray
Requires-Dist: lxml (>=4.6)
Requires-Dist: setuptools (~=50.3.2)
Requires-Dist: six (==1.15.0)
